{
  "data": [
    {
      "code": "600166.SH",
      "name": "福田汽车",
      "price": 3.68,
      "pct_change": -1.6,
      "pe": 19.64,
      "pb": 1.9,
      "market_cap": 29136033351,
      "turnover_rate": 3.58,
      "tech_score": 57,
      "tech_trend": 23,
      "tech_momentum": 15,
      "tech_volume": 9,
      "fund_score": 48,
      "fund_valuation": 20,
      "fund_profit": 0,
      "fund_growth": 16,
      "fund_liquidity": 12,
      "total_score": 55.2,
      "signals": [
        {
          "type": "bullish",
          "signal": "多头排列",
          "desc": "短中长期均线呈多头排列"
        },
        {
          "type": "bearish",
          "signal": "RSI超买",
          "desc": "RSI=76.5，处于超买区域"
        },
        {
          "type": "neutral",
          "signal": "放量",
          "desc": "成交量显著放大"
        }
      ],
      "recommendation": "观望"
    },
    {
      "code": "300014.SZ",
      "name": "亿纬锂能",
      "price": 72.35,
      "pct_change": 0.67,
      "pe": 37.67,
      "pb": 3.57,
      "market_cap": 155721560969,
      "turnover_rate": 2.5,
      "tech_score": 56,
      "tech_trend": 23,
      "tech_momentum": 20,
      "tech_volume": 3,
      "fund_score": 50,
      "fund_valuation": 10,
      "fund_profit": 0,
      "fund_growth": 20,
      "fund_liquidity": 20,
      "total_score": 54.8,
      "signals": [
        {
          "type": "bullish",
          "signal": "多头排列",
          "desc": "短中长期均线呈多头排列"
        }
      ],
      "recommendation": "观望"
    },
    {
      "code": "300558.SZ",
      "name": "贝达药业",
      "price": 49.63,
      "pct_change": -0.54,
      "pe": 22.13,
      "pb": 3.07,
      "market_cap": 20881020628,
      "turnover_rate": 3.63,
      "tech_score": 55,
      "tech_trend": 14,
      "tech_momentum": 23,
      "tech_volume": 13,
      "fund_score": 43,
      "fund_valuation": 15,
      "fund_profit": 0,
      "fund_growth": 16,
      "fund_liquidity": 12,
      "total_score": 52.6,
      "signals": [
        {
          "type": "bullish",
          "signal": "多头排列",
          "desc": "短中长期均线呈多头排列"
        },
        {
          "type": "bearish",
          "signal": "触及上轨",
          "desc": "价格触及布林带上轨，可能回调"
        },
        {
          "type": "neutral",
          "signal": "放量",
          "desc": "成交量显著放大"
        }
      ],
      "recommendation": "观望"
    },
    {
      "code": "600126.SH",
      "name": "杭钢股份",
      "price": 10.64,
      "pct_change": 2.01,
      "pe": 1488.6,
      "pb": 1.85,
      "market_cap": 35933291843,
      "turnover_rate": 8.72,
      "tech_score": 57,
      "tech_trend": 23,
      "tech_momentum": 23,
      "tech_volume": 6,
      "fund_score": 29,
      "fund_valuation": 5,
      "fund_profit": 0,
      "fund_growth": 16,
      "fund_liquidity": 8,
      "total_score": 51.4,
      "signals": [
        {
          "type": "bullish",
          "signal": "多头排列",
          "desc": "短中长期均线呈多头排列"
        }
      ],
      "recommendation": "观望"
    },
    {
      "code": "600875.SH",
      "name": "东方电气",
      "price": 41.43,
      "pct_change": -5.45,
      "pe": 37.4,
      "pb": 3.17,
      "market_cap": 143279868306,
      "turnover_rate": 3.28,
      "tech_score": 54,
      "tech_trend": 23,
      "tech_momentum": 15,
      "tech_volume": 6,
      "fund_score": 35,
      "fund_valuation": 10,
      "fund_profit": 0,
      "fund_growth": 5,
      "fund_liquidity": 20,
      "total_score": 50.2,
      "signals": [
        {
          "type": "bullish",
          "signal": "多头排列",
          "desc": "短中长期均线呈多头排列"
        },
        {
          "type": "bearish",
          "signal": "RSI超买",
          "desc": "RSI=70.2，处于超买区域"
        },
        {
          "type": "bearish",
          "signal": "KDJ超买",
          "desc": "KDJ指标处于超买区域"
        }
      ],
      "recommendation": "观望"
    },
    {
      "code": "603118.SH",
      "name": "共进股份",
      "price": 15.12,
      "pct_change": 3.77,
      "pe": 103.46,
      "pb": 2.36,
      "market_cap": 11903619259,
      "turnover_rate": 9.04,
      "tech_score": 56,
      "tech_trend": 23,
      "tech_momentum": 20,
      "tech_volume": 3,
      "fund_score": 23,
      "fund_valuation": 5,
      "fund_profit": 0,
      "fund_growth": 10,
      "fund_liquidity": 8,
      "total_score": 49.4,
      "signals": [
        {
          "type": "bullish",
          "signal": "多头排列",
          "desc": "短中长期均线呈多头排列"
        }
      ],
      "recommendation": "观望"
    },
    {
      "code": "300323.SZ",
      "name": "华灿光电",
      "price": 10.81,
      "pct_change": 1.31,
      "pe": -40.05,
      "pb": 2.67,
      "market_cap": 17544616996,
      "turnover_rate": 5.76,
      "tech_score": 56,
      "tech_trend": 23,
      "tech_momentum": 20,
      "tech_volume": 3,
      "fund_score": 23,
      "fund_valuation": 5,
      "fund_profit": 0,
      "fund_growth": 10,
      "fund_liquidity": 8,
      "total_score": 49.4,
      "signals": [
        {
          "type": "bullish",
          "signal": "多头排列",
          "desc": "短中长期均线呈多头排列"
        }
      ],
      "recommendation": "观望"
    },
    {
      "code": "300054.SZ",
      "name": "鼎龙股份",
      "price": 56.91,
      "pct_change": 1.72,
      "pe": 74.92,
      "pb": 10.39,
      "market_cap": 53954562514,
      "turnover_rate": 4.4,
      "tech_score": 51,
      "tech_trend": 23,
      "tech_momentum": 15,
      "tech_volume": 3,
      "fund_score": 40,
      "fund_valuation": 0,
      "fund_profit": 0,
      "fund_growth": 20,
      "fund_liquidity": 20,
      "total_score": 48.8,
      "signals": [
        {
          "type": "bullish",
          "signal": "多头排列",
          "desc": "短中长期均线呈多头排列"
        },
        {
          "type": "bearish",
          "signal": "RSI超买",
          "desc": "RSI=79.6，处于超买区域"
        }
      ],
      "recommendation": "观望"
    },
    {
      "code": "002080.SZ",
      "name": "中材科技",
      "price": 52.11,
      "pct_change": -1.9,
      "pe": 48.11,
      "pb": 4.39,
      "market_cap": 87447019962,
      "turnover_rate": 1.94,
      "tech_score": 51,
      "tech_trend": 23,
      "tech_momentum": 12,
      "tech_volume": 6,
      "fund_score": 40,
      "fund_valuation": 0,
      "fund_profit": 0,
      "fund_growth": 20,
      "fund_liquidity": 20,
      "total_score": 48.8,
      "signals": [
        {
          "type": "bullish",
          "signal": "多头排列",
          "desc": "短中长期均线呈多头排列"
        },
        {
          "type": "bearish",
          "signal": "RSI超买",
          "desc": "RSI=82.0，处于超买区域"
        },
        {
          "type": "bearish",
          "signal": "KDJ超买",
          "desc": "KDJ指标处于超买区域"
        }
      ],
      "recommendation": "观望"
    },
    {
      "code": "300782.SZ",
      "name": "卓胜微",
      "price": 103.13,
      "pct_change": -1.57,
      "pe": -205.84,
      "pb": 5.57,
      "market_cap": 55168692010,
      "turnover_rate": 3.99,
      "tech_score": 51,
      "tech_trend": 23,
      "tech_momentum": 20,
      "tech_volume": 3,
      "fund_score": 40,
      "fund_valuation": 0,
      "fund_profit": 0,
      "fund_growth": 20,
      "fund_liquidity": 20,
      "total_score": 48.8,
      "signals": [
        {
          "type": "bullish",
          "signal": "多头排列",
          "desc": "短中长期均线呈多头排列"
        }
      ],
      "recommendation": "观望"
    }
  ],
  "timestamp": "2026-04-24 13:40:46"
}